README.md
setup.py
tinylimit/__init__.py
tinylimit.egg-info/PKG-INFO
tinylimit.egg-info/SOURCES.txt
tinylimit.egg-info/dependency_links.txt
tinylimit.egg-info/top_level.txt