Metadata-Version: 2.1
Name: tinylimit
Version: 0.1.0
Summary: tinylimit is a python modules that limits the calling rate of a function
Home-page: https://github.com/jamesqin-cn/tinylimit
Author: jamesqin
Author-email: jamesqin@vip.qq.com
License: MIT
Platform: any
Classifier: Intended Audience :: Developers
Classifier: Operating System :: OS Independent
Classifier: Topic :: Utilities
Classifier: Topic :: Software Development :: Libraries :: Python Modules
Classifier: Programming Language :: Python
Classifier: Programming Language :: Python :: 2
Classifier: Programming Language :: Python :: 2.7
Classifier: Programming Language :: Python :: 3
Classifier: Programming Language :: Python :: 3.7
